<?xml version="1.0" encoding="utf-8" ?>
<dwsync>
<file name="icons.css" server="C:/Users/basil/Desktop/Work/On Going/Play2Learn/Ready For Web/Components/" local="132100406189441481" remote="132100406180000000" Dst="0" />
<file name="_atoms.scss" server="C:/Users/basil/Desktop/Work/On Going/Play2Learn/Ready For Web/Components/" local="132100361639164382" remote="132100361630000000" Dst="0" />
<file name="_atoms.css" server="C:/Users/basil/Desktop/Work/On Going/Play2Learn/Ready For Web/Components/" local="132100192868376638" remote="132100192860000000" Dst="0" />
<file name="doc_styles.scss" server="C:/Users/basil/Desktop/Work/On Going/Play2Learn/Ready For Web/Components/" local="132100448051581847" remote="132100448050000000" Dst="0" />
<file name="doc_styles.css" server="C:/Users/basil/Desktop/Work/On Going/Play2Learn/Ready For Web/Components/" local="132100448063607127" remote="132100448060000000" Dst="0" />
<file name="doc_grid.scss" server="C:/Users/basil/Desktop/Work/On Going/Play2Learn/Ready For Web/Components/" local="132100283237264384" remote="132100283230000000" Dst="0" />
<file name="doc_grid.css" server="C:/Users/basil/Desktop/Work/On Going/Play2Learn/Ready For Web/Components/" local="132100283258872050" remote="132100283250000000" Dst="0" />
<file name="_buttons.scss" server="C:/Users/basil/Desktop/Work/On Going/Play2Learn/Ready For Web/Components/" local="132100388254319544" remote="132100388250000000" Dst="0" />
<file name="_buttons.css" server="C:/Users/basil/Desktop/Work/On Going/Play2Learn/Ready For Web/Components/" local="132100217503587258" remote="132100217500000000" Dst="0" />
</dwsync>